akvile_turing_calculator/__init__.py
akvile_turing_calculator/calculator.py
akvile_turing_calculator-0.1.2.dist-info/LICENSE
akvile_turing_calculator-0.1.2.dist-info/METADATA
akvile_turing_calculator-0.1.2.dist-info/WHEEL
akvile_turing_calculator-0.1.2.dist-info/RECORD
