Metadata-Version: 2.1
Name: akvile-turing-calculator
Version: 0.1.2
Summary: Calculator module for Turing College Data Science course Module 1 Sprint 1. Performs basic calculations with internal memory.
License: MIT
Author: GallantYami
Author-email: landaiteakvile@gmail.com
Requires-Python: >=3.8,<4.0
Classifier: License :: OSI Approved :: MIT License
Classifier: Programming Language :: Python :: 3
Classifier: Programming Language :: Python :: 3.8
Classifier: Programming Language :: Python :: 3.9
Classifier: Programming Language :: Python :: 3.10
Classifier: Programming Language :: Python :: 3.11
